mandsapplicationform/__init__.py
mandsapplicationform/fixtures.py
mandsapplicationform/features/__init__.py
mandsapplicationform/features/test_steps.py
mandsapplicationform/features/hooks/conftest.py
mandsapplicationform/models/__init__.py
mandsapplicationform/models/application_form.py
mandsapplicationform/models/customer_portal.py
mandsapplicationform/models/customer_portal_web_api.py
mandsapplicationform/steps/customer_portal_web_api_steps.py
mandsapplicationform/steps/mands_application_form_steps.py
mandsapplicationform-0.0.1.dist-info/METADATA
mandsapplicationform-0.0.1.dist-info/WHEEL
mandsapplicationform-0.0.1.dist-info/top_level.txt
mandsapplicationform-0.0.1.dist-info/RECORD
